<?xml version="1.0" encoding="UTF-8" ?>
<!DOCTYPE mapper PUBLIC "-//mybatis.org//DTD Mapper 3.0//EN" "http://mybatis.org/dtd/mybatis-3-mapper.dtd" >
<mapper namespace="pams.repository.dao.SvClsCustinfoMapper" >
  <resultMap id="BaseResultMap" type="pams.repository.model.SvClsCustinfo" >
    <!--
      WARNING - @mbggenerated
      This element is automatically generated by MyBatis Generator, do not modify.
      This element was generated on Tue Dec 18 13:28:46 CST 2012.
    -->
    <id column="GUID" property="guid" jdbcType="VARCHAR" />
    <result column="BRANCH_NAME" property="branchName" jdbcType="VARCHAR" />
    <result column="BRANCH_ID" property="branchId" jdbcType="VARCHAR" />
    <result column="CUST_NAME" property="custName" jdbcType="VARCHAR" />
    <result column="CERT_TYPE" property="certType" jdbcType="VARCHAR" />
    <result column="CERT_NO" property="certNo" jdbcType="VARCHAR" />
    <result column="CONTACT_INFO1" property="contactInfo1" jdbcType="VARCHAR" />
    <result column="CONTACT_INFO2" property="contactInfo2" jdbcType="VARCHAR" />
    <result column="AUM_MONTH_CURR" property="aumMonthCurr" jdbcType="DECIMAL" />
    <result column="AUM_MONTH_LAST" property="aumMonthLast" jdbcType="DECIMAL" />
    <result column="AUM_TIMEPOINT_DEP" property="aumTimepointDep" jdbcType="DECIMAL" />
    <result column="LOAN_BAL" property="loanBal" jdbcType="DECIMAL" />
    <result column="OPENACT_BRANCH_ID" property="openactBranchId" jdbcType="VARCHAR" />
    <result column="OPENACT_BRANCH_NAME" property="openactBranchName" jdbcType="VARCHAR" />
    <result column="CTS_MARGIN_BAL" property="ctsMarginBal" jdbcType="DECIMAL" />
    <result column="RPT_DATE" property="rptDate" jdbcType="VARCHAR" />
    <result column="RPT_TYPE" property="rptType" jdbcType="VARCHAR" />
    <result column="OPER_ID" property="operId" jdbcType="VARCHAR" />
    <result column="OPER_DATE" property="operDate" jdbcType="TIMESTAMP" />
    <result column="IMP_DATE" property="impDate" jdbcType="TIMESTAMP" />
    <result column="DELETE_FLAG" property="deleteFlag" jdbcType="VARCHAR" />
  </resultMap>
  <sql id="Example_Where_Clause" >
    <!--
      WARNING - @mbggenerated
      This element is automatically generated by MyBatis Generator, do not modify.
      This element was generated on Tue Dec 18 13:28:46 CST 2012.
    -->
    <where >
      <foreach collection="oredCriteria" item="criteria" separator="or" >
        <if test="criteria.valid" >
          <trim prefix="(" suffix=")" prefixOverrides="and" >
            <foreach collection="criteria.criteria" item="criterion" >
              <choose >
                <when test="criterion.noValue" >
                  and ${criterion.condition}
                </when>
                <when test="criterion.singleValue" >
                  and ${criterion.condition} #{criterion.value}
                </when>
                <when test="criterion.betweenValue" >
                  and ${criterion.condition} #{criterion.value} and #{criterion.secondValue}
                </when>
                <when test="criterion.listValue" >
                  and ${criterion.condition}
                  <foreach collection="criterion.value" item="listItem" open="(" close=")" separator="," >
                    #{listItem}
                  </foreach>
                </when>
              </choose>
            </foreach>
          </trim>
        </if>
      </foreach>
    </where>
  </sql>
  <sql id="Update_By_Example_Where_Clause" >
    <!--
      WARNING - @mbggenerated
      This element is automatically generated by MyBatis Generator, do not modify.
      This element was generated on Tue Dec 18 13:28:46 CST 2012.
    -->
    <where >
      <foreach collection="example.oredCriteria" item="criteria" separator="or" >
        <if test="criteria.valid" >
          <trim prefix="(" suffix=")" prefixOverrides="and" >
            <foreach collection="criteria.criteria" item="criterion" >
              <choose >
                <when test="criterion.noValue" >
                  and ${criterion.condition}
                </when>
                <when test="criterion.singleValue" >
                  and ${criterion.condition} #{criterion.value}
                </when>
                <when test="criterion.betweenValue" >
                  and ${criterion.condition} #{criterion.value} and #{criterion.secondValue}
                </when>
                <when test="criterion.listValue" >
                  and ${criterion.condition}
                  <foreach collection="criterion.value" item="listItem" open="(" close=")" separator="," >
                    #{listItem}
                  </foreach>
                </when>
              </choose>
            </foreach>
          </trim>
        </if>
      </foreach>
    </where>
  </sql>
  <sql id="Base_Column_List" >
    <!--
      WARNING - @mbggenerated
      This element is automatically generated by MyBatis Generator, do not modify.
      This element was generated on Tue Dec 18 13:28:46 CST 2012.
    -->
    GUID, BRANCH_NAME, BRANCH_ID, CUST_NAME, CERT_TYPE, CERT_NO, CONTACT_INFO1, CONTACT_INFO2, 
    AUM_MONTH_CURR, AUM_MONTH_LAST, AUM_TIMEPOINT_DEP, LOAN_BAL, OPENACT_BRANCH_ID, OPENACT_BRANCH_NAME, 
    CTS_MARGIN_BAL, RPT_DATE, RPT_TYPE, OPER_ID, OPER_DATE, IMP_DATE, DELETE_FLAG
  </sql>
  <select id="selectByExample" resultMap="BaseResultMap" parameterType="pams.repository.model.SvClsCustinfoExample" >
    <!--
      WARNING - @mbggenerated
      This element is automatically generated by MyBatis Generator, do not modify.
      This element was generated on Tue Dec 18 13:28:46 CST 2012.
    -->
    select
    <if test="distinct" >
      distinct
    </if>
    <include refid="Base_Column_List" />
    from SV_CLS_CUSTINFO
    <if test="_parameter != null" >
      <include refid="Example_Where_Clause" />
    </if>
    <if test="orderByClause != null" >
      order by ${orderByClause}
    </if>
  </select>
  <select id="selectByPrimaryKey" resultMap="BaseResultMap" parameterType="java.lang.String" >
    <!--
      WARNING - @mbggenerated
      This element is automatically generated by MyBatis Generator, do not modify.
      This element was generated on Tue Dec 18 13:28:46 CST 2012.
    -->
    select 
    <include refid="Base_Column_List" />
    from SV_CLS_CUSTINFO
    where GUID = #{guid,jdbcType=VARCHAR}
  </select>
  <delete id="deleteByPrimaryKey" parameterType="java.lang.String" >
    <!--
      WARNING - @mbggenerated
      This element is automatically generated by MyBatis Generator, do not modify.
      This element was generated on Tue Dec 18 13:28:46 CST 2012.
    -->
    delete from SV_CLS_CUSTINFO
    where GUID = #{guid,jdbcType=VARCHAR}
  </delete>
  <delete id="deleteByExample" parameterType="pams.repository.model.SvClsCustinfoExample" >
    <!--
      WARNING - @mbggenerated
      This element is automatically generated by MyBatis Generator, do not modify.
      This element was generated on Tue Dec 18 13:28:46 CST 2012.
    -->
    delete from SV_CLS_CUSTINFO
    <if test="_parameter != null" >
      <include refid="Example_Where_Clause" />
    </if>
  </delete>
  <insert id="insert" parameterType="pams.repository.model.SvClsCustinfo" >
    <!--
      WARNING - @mbggenerated
      This element is automatically generated by MyBatis Generator, do not modify.
      This element was generated on Tue Dec 18 13:28:46 CST 2012.
    -->
    <selectKey resultType="java.lang.String" keyProperty="guid" order="BEFORE" >
      select sys_guid() from dual
    </selectKey>
    insert into SV_CLS_CUSTINFO (GUID, BRANCH_NAME, BRANCH_ID, 
      CUST_NAME, CERT_TYPE, CERT_NO, 
      CONTACT_INFO1, CONTACT_INFO2, AUM_MONTH_CURR, 
      AUM_MONTH_LAST, AUM_TIMEPOINT_DEP, LOAN_BAL, 
      OPENACT_BRANCH_ID, OPENACT_BRANCH_NAME, CTS_MARGIN_BAL, 
      RPT_DATE, RPT_TYPE, OPER_ID, 
      OPER_DATE, IMP_DATE, DELETE_FLAG
      )
    values (#{guid,jdbcType=VARCHAR}, #{branchName,jdbcType=VARCHAR}, #{branchId,jdbcType=VARCHAR}, 
      #{custName,jdbcType=VARCHAR}, #{certType,jdbcType=VARCHAR}, #{certNo,jdbcType=VARCHAR}, 
      #{contactInfo1,jdbcType=VARCHAR}, #{contactInfo2,jdbcType=VARCHAR}, #{aumMonthCurr,jdbcType=DECIMAL}, 
      #{aumMonthLast,jdbcType=DECIMAL}, #{aumTimepointDep,jdbcType=DECIMAL}, #{loanBal,jdbcType=DECIMAL}, 
      #{openactBranchId,jdbcType=VARCHAR}, #{openactBranchName,jdbcType=VARCHAR}, #{ctsMarginBal,jdbcType=DECIMAL}, 
      #{rptDate,jdbcType=VARCHAR}, #{rptType,jdbcType=VARCHAR}, #{operId,jdbcType=VARCHAR}, 
      #{operDate,jdbcType=TIMESTAMP}, #{impDate,jdbcType=TIMESTAMP}, #{deleteFlag,jdbcType=VARCHAR}
      )
  </insert>
  <insert id="insertSelective" parameterType="pams.repository.model.SvClsCustinfo" >
    <!--
      WARNING - @mbggenerated
      This element is automatically generated by MyBatis Generator, do not modify.
      This element was generated on Tue Dec 18 13:28:46 CST 2012.
    -->
    <selectKey resultType="java.lang.String" keyProperty="guid" order="BEFORE" >
      select sys_guid() from dual
    </selectKey>
    insert into SV_CLS_CUSTINFO
    <trim prefix="(" suffix=")" suffixOverrides="," >
      GUID,
      <if test="branchName != null" >
        BRANCH_NAME,
      </if>
      <if test="branchId != null" >
        BRANCH_ID,
      </if>
      <if test="custName != null" >
        CUST_NAME,
      </if>
      <if test="certType != null" >
        CERT_TYPE,
      </if>
      <if test="certNo != null" >
        CERT_NO,
      </if>
      <if test="contactInfo1 != null" >
        CONTACT_INFO1,
      </if>
      <if test="contactInfo2 != null" >
        CONTACT_INFO2,
      </if>
      <if test="aumMonthCurr != null" >
        AUM_MONTH_CURR,
      </if>
      <if test="aumMonthLast != null" >
        AUM_MONTH_LAST,
      </if>
      <if test="aumTimepointDep != null" >
        AUM_TIMEPOINT_DEP,
      </if>
      <if test="loanBal != null" >
        LOAN_BAL,
      </if>
      <if test="openactBranchId != null" >
        OPENACT_BRANCH_ID,
      </if>
      <if test="openactBranchName != null" >
        OPENACT_BRANCH_NAME,
      </if>
      <if test="ctsMarginBal != null" >
        CTS_MARGIN_BAL,
      </if>
      <if test="rptDate != null" >
        RPT_DATE,
      </if>
      <if test="rptType != null" >
        RPT_TYPE,
      </if>
      <if test="operId != null" >
        OPER_ID,
      </if>
      <if test="operDate != null" >
        OPER_DATE,
      </if>
      <if test="impDate != null" >
        IMP_DATE,
      </if>
      <if test="deleteFlag != null" >
        DELETE_FLAG,
      </if>
    </trim>
    <trim prefix="values (" suffix=")" suffixOverrides="," >
      #{guid,jdbcType=VARCHAR},
      <if test="branchName != null" >
        #{branchName,jdbcType=VARCHAR},
      </if>
      <if test="branchId != null" >
        #{branchId,jdbcType=VARCHAR},
      </if>
      <if test="custName != null" >
        #{custName,jdbcType=VARCHAR},
      </if>
      <if test="certType != null" >
        #{certType,jdbcType=VARCHAR},
      </if>
      <if test="certNo != null" >
        #{certNo,jdbcType=VARCHAR},
      </if>
      <if test="contactInfo1 != null" >
        #{contactInfo1,jdbcType=VARCHAR},
      </if>
      <if test="contactInfo2 != null" >
        #{contactInfo2,jdbcType=VARCHAR},
      </if>
      <if test="aumMonthCurr != null" >
        #{aumMonthCurr,jdbcType=DECIMAL},
      </if>
      <if test="aumMonthLast != null" >
        #{aumMonthLast,jdbcType=DECIMAL},
      </if>
      <if test="aumTimepointDep != null" >
        #{aumTimepointDep,jdbcType=DECIMAL},
      </if>
      <if test="loanBal != null" >
        #{loanBal,jdbcType=DECIMAL},
      </if>
      <if test="openactBranchId != null" >
        #{openactBranchId,jdbcType=VARCHAR},
      </if>
      <if test="openactBranchName != null" >
        #{openactBranchName,jdbcType=VARCHAR},
      </if>
      <if test="ctsMarginBal != null" >
        #{ctsMarginBal,jdbcType=DECIMAL},
      </if>
      <if test="rptDate != null" >
        #{rptDate,jdbcType=VARCHAR},
      </if>
      <if test="rptType != null" >
        #{rptType,jdbcType=VARCHAR},
      </if>
      <if test="operId != null" >
        #{operId,jdbcType=VARCHAR},
      </if>
      <if test="operDate != null" >
        #{operDate,jdbcType=TIMESTAMP},
      </if>
      <if test="impDate != null" >
        #{impDate,jdbcType=TIMESTAMP},
      </if>
      <if test="deleteFlag != null" >
        #{deleteFlag,jdbcType=VARCHAR},
      </if>
    </trim>
  </insert>
  <select id="countByExample" parameterType="pams.repository.model.SvClsCustinfoExample" resultType="java.lang.Integer" >
    <!--
      WARNING - @mbggenerated
      This element is automatically generated by MyBatis Generator, do not modify.
      This element was generated on Tue Dec 18 13:28:46 CST 2012.
    -->
    select count(*) from SV_CLS_CUSTINFO
    <if test="_parameter != null" >
      <include refid="Example_Where_Clause" />
    </if>
  </select>
  <update id="updateByExampleSelective" parameterType="map" >
    <!--
      WARNING - @mbggenerated
      This element is automatically generated by MyBatis Generator, do not modify.
      This element was generated on Tue Dec 18 13:28:46 CST 2012.
    -->
    update SV_CLS_CUSTINFO
    <set >
      <if test="record.guid != null" >
        GUID = #{record.guid,jdbcType=VARCHAR},
      </if>
      <if test="record.branchName != null" >
        BRANCH_NAME = #{record.branchName,jdbcType=VARCHAR},
      </if>
      <if test="record.branchId != null" >
        BRANCH_ID = #{record.branchId,jdbcType=VARCHAR},
      </if>
      <if test="record.custName != null" >
        CUST_NAME = #{record.custName,jdbcType=VARCHAR},
      </if>
      <if test="record.certType != null" >
        CERT_TYPE = #{record.certType,jdbcType=VARCHAR},
      </if>
      <if test="record.certNo != null" >
        CERT_NO = #{record.certNo,jdbcType=VARCHAR},
      </if>
      <if test="record.contactInfo1 != null" >
        CONTACT_INFO1 = #{record.contactInfo1,jdbcType=VARCHAR},
      </if>
      <if test="record.contactInfo2 != null" >
        CONTACT_INFO2 = #{record.contactInfo2,jdbcType=VARCHAR},
      </if>
      <if test="record.aumMonthCurr != null" >
        AUM_MONTH_CURR = #{record.aumMonthCurr,jdbcType=DECIMAL},
      </if>
      <if test="record.aumMonthLast != null" >
        AUM_MONTH_LAST = #{record.aumMonthLast,jdbcType=DECIMAL},
      </if>
      <if test="record.aumTimepointDep != null" >
        AUM_TIMEPOINT_DEP = #{record.aumTimepointDep,jdbcType=DECIMAL},
      </if>
      <if test="record.loanBal != null" >
        LOAN_BAL = #{record.loanBal,jdbcType=DECIMAL},
      </if>
      <if test="record.openactBranchId != null" >
        OPENACT_BRANCH_ID = #{record.openactBranchId,jdbcType=VARCHAR},
      </if>
      <if test="record.openactBranchName != null" >
        OPENACT_BRANCH_NAME = #{record.openactBranchName,jdbcType=VARCHAR},
      </if>
      <if test="record.ctsMarginBal != null" >
        CTS_MARGIN_BAL = #{record.ctsMarginBal,jdbcType=DECIMAL},
      </if>
      <if test="record.rptDate != null" >
        RPT_DATE = #{record.rptDate,jdbcType=VARCHAR},
      </if>
      <if test="record.rptType != null" >
        RPT_TYPE = #{record.rptType,jdbcType=VARCHAR},
      </if>
      <if test="record.operId != null" >
        OPER_ID = #{record.operId,jdbcType=VARCHAR},
      </if>
      <if test="record.operDate != null" >
        OPER_DATE = #{record.operDate,jdbcType=TIMESTAMP},
      </if>
      <if test="record.impDate != null" >
        IMP_DATE = #{record.impDate,jdbcType=TIMESTAMP},
      </if>
      <if test="record.deleteFlag != null" >
        DELETE_FLAG = #{record.deleteFlag,jdbcType=VARCHAR},
      </if>
    </set>
    <if test="_parameter != null" >
      <include refid="Update_By_Example_Where_Clause" />
    </if>
  </update>
  <update id="updateByExample" parameterType="map" >
    <!--
      WARNING - @mbggenerated
      This element is automatically generated by MyBatis Generator, do not modify.
      This element was generated on Tue Dec 18 13:28:47 CST 2012.
    -->
    update SV_CLS_CUSTINFO
    set GUID = #{record.guid,jdbcType=VARCHAR},
      BRANCH_NAME = #{record.branchName,jdbcType=VARCHAR},
      BRANCH_ID = #{record.branchId,jdbcType=VARCHAR},
      CUST_NAME = #{record.custName,jdbcType=VARCHAR},
      CERT_TYPE = #{record.certType,jdbcType=VARCHAR},
      CERT_NO = #{record.certNo,jdbcType=VARCHAR},
      CONTACT_INFO1 = #{record.contactInfo1,jdbcType=VARCHAR},
      CONTACT_INFO2 = #{record.contactInfo2,jdbcType=VARCHAR},
      AUM_MONTH_CURR = #{record.aumMonthCurr,jdbcType=DECIMAL},
      AUM_MONTH_LAST = #{record.aumMonthLast,jdbcType=DECIMAL},
      AUM_TIMEPOINT_DEP = #{record.aumTimepointDep,jdbcType=DECIMAL},
      LOAN_BAL = #{record.loanBal,jdbcType=DECIMAL},
      OPENACT_BRANCH_ID = #{record.openactBranchId,jdbcType=VARCHAR},
      OPENACT_BRANCH_NAME = #{record.openactBranchName,jdbcType=VARCHAR},
      CTS_MARGIN_BAL = #{record.ctsMarginBal,jdbcType=DECIMAL},
      RPT_DATE = #{record.rptDate,jdbcType=VARCHAR},
      RPT_TYPE = #{record.rptType,jdbcType=VARCHAR},
      OPER_ID = #{record.operId,jdbcType=VARCHAR},
      OPER_DATE = #{record.operDate,jdbcType=TIMESTAMP},
      IMP_DATE = #{record.impDate,jdbcType=TIMESTAMP},
      DELETE_FLAG = #{record.deleteFlag,jdbcType=VARCHAR}
    <if test="_parameter != null" >
      <include refid="Update_By_Example_Where_Clause" />
    </if>
  </update>
  <update id="updateByPrimaryKeySelective" parameterType="pams.repository.model.SvClsCustinfo" >
    <!--
      WARNING - @mbggenerated
      This element is automatically generated by MyBatis Generator, do not modify.
      This element was generated on Tue Dec 18 13:28:47 CST 2012.
    -->
    update SV_CLS_CUSTINFO
    <set >
      <if test="branchName != null" >
        BRANCH_NAME = #{branchName,jdbcType=VARCHAR},
      </if>
      <if test="branchId != null" >
        BRANCH_ID = #{branchId,jdbcType=VARCHAR},
      </if>
      <if test="custName != null" >
        CUST_NAME = #{custName,jdbcType=VARCHAR},
      </if>
      <if test="certType != null" >
        CERT_TYPE = #{certType,jdbcType=VARCHAR},
      </if>
      <if test="certNo != null" >
        CERT_NO = #{certNo,jdbcType=VARCHAR},
      </if>
      <if test="contactInfo1 != null" >
        CONTACT_INFO1 = #{contactInfo1,jdbcType=VARCHAR},
      </if>
      <if test="contactInfo2 != null" >
        CONTACT_INFO2 = #{contactInfo2,jdbcType=VARCHAR},
      </if>
      <if test="aumMonthCurr != null" >
        AUM_MONTH_CURR = #{aumMonthCurr,jdbcType=DECIMAL},
      </if>
      <if test="aumMonthLast != null" >
        AUM_MONTH_LAST = #{aumMonthLast,jdbcType=DECIMAL},
      </if>
      <if test="aumTimepointDep != null" >
        AUM_TIMEPOINT_DEP = #{aumTimepointDep,jdbcType=DECIMAL},
      </if>
      <if test="loanBal != null" >
        LOAN_BAL = #{loanBal,jdbcType=DECIMAL},
      </if>
      <if test="openactBranchId != null" >
        OPENACT_BRANCH_ID = #{openactBranchId,jdbcType=VARCHAR},
      </if>
      <if test="openactBranchName != null" >
        OPENACT_BRANCH_NAME = #{openactBranchName,jdbcType=VARCHAR},
      </if>
      <if test="ctsMarginBal != null" >
        CTS_MARGIN_BAL = #{ctsMarginBal,jdbcType=DECIMAL},
      </if>
      <if test="rptDate != null" >
        RPT_DATE = #{rptDate,jdbcType=VARCHAR},
      </if>
      <if test="rptType != null" >
        RPT_TYPE = #{rptType,jdbcType=VARCHAR},
      </if>
      <if test="operId != null" >
        OPER_ID = #{operId,jdbcType=VARCHAR},
      </if>
      <if test="operDate != null" >
        OPER_DATE = #{operDate,jdbcType=TIMESTAMP},
      </if>
      <if test="impDate != null" >
        IMP_DATE = #{impDate,jdbcType=TIMESTAMP},
      </if>
      <if test="deleteFlag != null" >
        DELETE_FLAG = #{deleteFlag,jdbcType=VARCHAR},
      </if>
    </set>
    where GUID = #{guid,jdbcType=VARCHAR}
  </update>
  <update id="updateByPrimaryKey" parameterType="pams.repository.model.SvClsCustinfo" >
    <!--
      WARNING - @mbggenerated
      This element is automatically generated by MyBatis Generator, do not modify.
      This element was generated on Tue Dec 18 13:28:47 CST 2012.
    -->
    update SV_CLS_CUSTINFO
    set BRANCH_NAME = #{branchName,jdbcType=VARCHAR},
      BRANCH_ID = #{branchId,jdbcType=VARCHAR},
      CUST_NAME = #{custName,jdbcType=VARCHAR},
      CERT_TYPE = #{certType,jdbcType=VARCHAR},
      CERT_NO = #{certNo,jdbcType=VARCHAR},
      CONTACT_INFO1 = #{contactInfo1,jdbcType=VARCHAR},
      CONTACT_INFO2 = #{contactInfo2,jdbcType=VARCHAR},
      AUM_MONTH_CURR = #{aumMonthCurr,jdbcType=DECIMAL},
      AUM_MONTH_LAST = #{aumMonthLast,jdbcType=DECIMAL},
      AUM_TIMEPOINT_DEP = #{aumTimepointDep,jdbcType=DECIMAL},
      LOAN_BAL = #{loanBal,jdbcType=DECIMAL},
      OPENACT_BRANCH_ID = #{openactBranchId,jdbcType=VARCHAR},
      OPENACT_BRANCH_NAME = #{openactBranchName,jdbcType=VARCHAR},
      CTS_MARGIN_BAL = #{ctsMarginBal,jdbcType=DECIMAL},
      RPT_DATE = #{rptDate,jdbcType=VARCHAR},
      RPT_TYPE = #{rptType,jdbcType=VARCHAR},
      OPER_ID = #{operId,jdbcType=VARCHAR},
      OPER_DATE = #{operDate,jdbcType=TIMESTAMP},
      IMP_DATE = #{impDate,jdbcType=TIMESTAMP},
      DELETE_FLAG = #{deleteFlag,jdbcType=VARCHAR}
    where GUID = #{guid,jdbcType=VARCHAR}
  </update>

    <select id="selectTest" resultType="Integer">
        select count(*)
          from SV_CLS_CUSTINFO
    </select>



</mapper>